Workbook

Sheet Index
A1: Juhayna (JUFO) — Full Database & Analysis · 2021 → Q1 2026
A3: 1. Income Statement | B3: Full annual in EGP + margins (formulas) + source column
A4: 2. Quarterly Data | B4: 21 quarters: revenue/gross/EBITDA/net + margins by formula
A5: 3. Seasonality | B5: Margin matrix by quarter + Ramadan-quarter column
A6: 4. Balance Sheet | B6: Full balance sheet — totals are formulas, balance checked
A7: 5. Cash Flow | B7: Operating/investing/financing + cash reconciliation formula
A8: 6. Working Capital | B8: DIO/DSO/DPO/CCC formulas — real payables 2021-2024
A9: 7. Revenue Breakdown | B9: Segments + domestic/export + growth drivers
A10: 8. Cost Breakdown | B10: Note 4 (COGS components) + Note 17 (inventory)
A11: 9. FX Differences | B11: Shown/shifted + reported vs adjusted profit (formulas)
A12: 10. Leverage & Returns | B12: Net debt, coverage, ROE/DuPont/ROIC — all formulas
A13: 11. Valuation | B13: Price is a blue cell → all multiples update automatically
A14: 12. 2026 Forecast | B14: Scenarios + quarterly split anchored to actual Q1
A15: 13. Management Commentary | B15: Documented findings from business results

Sheet Income Statement
A1: Consolidated Income Statement (EGP)
A2: Line item (EGP) | B2: 2021 | C2: 2022 | D2: 2023 | E2: 2024 | F2: 2025 | G2: Source
A3: Net revenue | B3: 8805974252 | C3: 11363960170 | D3: 16128101761 | E3: 24302616048 | F3: 29984446222 | G3: Audited consolidated
A4: Cost of sales | B4: -6278903539 | C4: -8458554544 | D4: -11906411622 | E4: -16912916624 | F4: -23103562055 | G4: Income statement
A5: Gross profit | B5: =B3+B4 -> 2527070713 | C5: =C3+C4 -> 2905405626 | D5: =D3+D4 -> 4221690139 | E5: =E3+E4 -> 7389699424 | F5: =F3+F4 -> 6880884167 | G5: Revenue + cost
A6: Gross margin % | B6: =B5/B3 -> 0.2869723 | C6: =C5/C3 -> 0.25566841 | D6: =D5/D3 -> 0.26175989 | E6: =E5/E3 -> 0.30407012 | F6: =F5/F3 -> 0.22948178 | G6: Gross / revenue
A7: Other operating income | B7: 41548292 | C7: 122415644 | D7: 178863933 | E7: 332938371 | F7: 325638100 | G7: Income statement
A8: Selling & marketing | B8: -1340271251 | C8: -1544969079 | D8: -1933987009 | E8: -2159669231 | F8: -2736787707 | G8: Income statement
A9: General & admin | B9: -272283318 | C9: -286403392 | D9: -388147620 | E9: -659201157 | F9: -831126207 | G9: Income statement
A10: Impairment / provision | B10: 0 | C10: 0 | D10: 5971372 | E10: 0 | F10: 0 | G10: Income statement
A11: Other expenses / credit losses | B11: -122143862 | C11: -171502831 | D11: -282461208 | E11: -210789892 | F11: -65316259 | G11: Income statement
A12: Operating result | B12: =B5+B7+B8+B9+B10+B11 -> 833920574 | C12: =C5+C7+C8+C9+C10+C11 -> 1024945968 | D12: =D5+D7+D8+D9+D10+D11 -> 1801929607 | E12: =E5+E7+E8+E9+E10+E11 -> 4692977515 | F12: =F5+F7+F8+F9+F10+F11 -> 3573292094 | G12: Sum of items above
A13: Operating margin % | B13: =B12/B3 -> 0.094699411 | C13: =C12/C3 -> 0.090192675 | D13: =D12/D3 -> 0.11172608 | E13: =E12/E3 -> 0.19310586 | F13: =F12/F3 -> 0.11917152 | G13: Operating / revenue
A14: Share of equity-method cos. | B14: 645136 | C14: 1809251 | D14: -1256023 | E14: 2355482 | F14: 0 | G14: Income statement
A15: Net financing cost | B15: -68187651 | C15: -123313682 | D15: -320893260 | E15: -596428158 | F15: -1168793931 | G15: Note 9
A16: Loss on sale of investment | B16: 0 | C16: 0 | D16: -115108535 | E16: -522059933 | F16: 0 | G16: Income statement
A17: Profit before tax | B17: =B12+B14+B15+B16 -> 766378059 | C17: =C12+C14+C15+C16 -> 903441537 | D17: =D12+D14+D15+D16 -> 1364671789 | E17: =E12+E14+E15+E16 -> 3576844906 | F17: =F12+F14+F15+F16 -> 2404498163 | G17: Formula
A18: Income tax | B18: -226962845 | C18: -272826682 | D18: -343211571 | E18: -841450390 | F18: -494403328 | G18: Income statement
A19: Tax true-up / deferred | B19: -13026096 | C19: 7384145 | D19: 0 | E19: 0 | F19: 0 | G19: To match reported EPS
A20: Net profit after tax | B20: =B17+B18+B19 -> 526389118 | C20: =C17+C18+C19 -> 637999000 | D20: =D17+D18+D19 -> 1021460218 | E20: =E17+E18+E19 -> 2735394516 | F20: =F17+F18+F19 -> 1910094835 | G20: Formula
A21: Net margin % | B21: =B20/B3 -> 0.059776364 | C21: =C20/C3 -> 0.056142312 | D21: =D20/D3 -> 0.063334187 | E21: =E20/E3 -> 0.11255556 | F21: =F20/F3 -> 0.063702855 | G21: Net / revenue
A22: EBITDA (mn) | B22: 1224 | C22: 1465 | D22: 2224 | E22: 4693 | F22: 4634 | G22: Business results
A23: Revenue growth % | B23: — | C23: =C3/B3-1 -> 0.29048301 | D23: =D3/C3-1 -> 0.41923251 | E23: =E3/D3-1 -> 0.50684913 | F23: =F3/E3-1 -> 0.233795 | G23: Year / prior − 1
A24: ⚠ 2024-2025: FX losses (344.8mn / 348mn) shifted to OCI under EAS 13 — profit here is "reported"; the adjusted figure is on the FX sheet. 2025 is the first year after consolidating 4 subsidiaries.

Sheet Quarterly Data
A1: Quarterly Data (EGP mn) — 21 quarters
A2: Metric (EGP) | B2: 1Q21 | C2: 2Q21 | D2: 3Q21 | E2: 4Q21 | F2: 1Q22 | G2: 2Q22 | H2: 3Q22 | I2: 4Q22 | J2: 1Q23 | K2: 2Q23 | L2: 3Q23 | M2: 4Q23 | N2: 1Q24 | O2: 2Q24 | P2: 3Q24 | Q2: 4Q24 | R2: 1Q25 | S2: 2Q25 | T2: 3Q25 | U2: 4Q25
A3: Net revenue | B3: 1861689122 | C3: 2226863636 | D3: 2435430424 | E3: 2281991070 | F3: 2403433446 | G3: 2761133770 | H3: 2996498775 | I3: 3202894179 | J3: 3423285226 | K3: 3730081032 | L3: 4500471406 | M3: 4474264097 | N3: 5758301967 | O3: 6035549981 | P3: 6863671472 | Q3: 5645092628 | R3: 6802910589 | S3: 7362177408 | T3: 7971607240 | U3: 7847750985
A4: Gross profit | B4: 542614912 | C4: 718065543 | D4: 661685152 | E4: 604705106 | F4: 641817404 | G4: 772638703 | H4: 680999419 | I4: 809950100 | J4: 1017338784 | K4: 910504506 | L4: 1072115667 | M4: 1221062075 | N4: 2204616820 | O4: 1928954980 | P4: 2035065549 | Q4: 1221731182 | R4: 1176834132 | S4: 1862885101 | T4: 1941619692 | U4: 1899545242
A5: Gross margin % | B5: =B4/B3 -> 0.29146376 | C5: =C4/C3 -> 0.322456 | D5: =D4/D3 -> 0.27169126 | E5: =E4/E3 -> 0.26499013 | F5: =F4/F3 -> 0.26704189 | G5: =G4/G3 -> 0.27982661 | H5: =H4/H3 -> 0.22726504 | I5: =I4/I3 -> 0.25288069 | ... U5: =U4/U3 -> 0.24204963
A6: EBITDA | B6: 260000000 | C6: 349000000 | D6: 335000000 | E6: 281000000 | F6: 279000000 | G6: 330000000 | H6: 340000000 | I6: 466000000 | J6: 594000000 | K6: 405000000 | L6: 576000000 | M6: 649000000 | N6: 1397000000 | O6: 1516000000 | P6: 1510000000 | Q6: 620000000 | R6: 1260000000 | S6: 1075000000 | T6: 1138000000 | U6: 1160000000
A7: EBITDA margin % | B7: =B6/B3 -> 0.13965812 | C7: =C6/C3 -> 0.15672266 | D7: =D6/D3 -> 0.13755269 | E7: =E6/E3 -> 0.12313808 | F7: =F6/F3 -> 0.11608393 | G7: =G6/G3 -> 0.11951612 | H7: =H6/H3 -> 0.11346576 | I7: =I6/I3 -> 0.14549341 | ... U7: =U6/U3 -> 0.14781305
A8: Net profit | B8: 123145654 | C8: 193065871 | D8: 173529864 | E8: 36647729 | F8: 144419705 | G8: 174529686 | H8: 155137340 | I8: 163912269 | J8: 339414732 | K8: 217015918 | L8: 322506055 | M8: 142523513 | N8: 478744970 | O8: 1001509233 | P8: 957550972 | Q8: 297549341 | R8: 299671870 | S8: 481511135 | T8: 490745113 | U8: 638166717
A9: Net margin % | B9: =B8/B3 -> 0.066147271 | C9: =C8/C3 -> 0.08669856 | D9: =D8/D3 -> 0.071252236 | E9: =E8/E3 -> 0.016059541 | F9: =F8/F3 -> 0.060088914 | G9: =G8/G3 -> 0.063209428 | H9: =H8/H3 -> 0.051772869 | I9: =I8/I3 -> 0.051176299 | ... U9: =U8/U3 -> 0.081318421
A10: ⚠ 2025 figures from business results (partly include consolidation effect). EBITDA 2021-2024 from business results — source not consistent across years; rebuild from statements for precise comparison.

Sheet Seasonality
A1: Seasonality — gross margin by quarter + Ramadan quarter
A2: Year | B2: Q1 | C2: Q2 | D2: Q3 | E2: Q4 | F2: Ramadan quarter | G2: Highest = Ramadan?
A3: 2021 | B3: 0.291 | C3: 0.322 | D3: 0.272 | E3: 0.265 | F3: Q2 | G3: Yes
A4: 2022 | B4: 0.267 | C4: 0.28 | D4: 0.227 | E4: 0.253 | F4: Q2 | G4: Yes
A5: 2023 | B5: 0.297 | C5: 0.244 | D5: 0.244 | E5: 0.273 | F5: Q1 | G5: Yes
A6: 2024 | B6: 0.383 | C6: 0.32 | D6: 0.296 | E6: 0.216 | F6: Q1 | G6: Yes
A7: 2025 | B7: 0.173 | C7: 0.253 | D7: 0.244 | E7: 0.242 | F7: Q1 | G7: No — see note
A8: Quarter average | B8: =AVERAGE(B3:B7) -> 0.2822 | C8: =AVERAGE(C3:C7) -> 0.2838 | D8: =AVERAGE(D3:D7) -> 0.2566 | E8: =AVERAGE(E3:E7) -> 0.2498
A10: ⚠ The highest annual margin sits in the quarter containing Ramadan (4/5 years). Ramadan 2026 fell entirely in Q1 → Q2 2026 will be weaker on margin. 2025 broke the pattern only because Ramadan coincided with a sharp devaluation shock.

Sheet Balance Sheet
A1: Statement of Financial Position (EGP)
A2: Item (EGP) | B2: 2021 | C2: 2022 | D2: 2023 | E2: 2024 | F2: 2025
A3: Non-current assets
A4: Property, plant & equipment | B4: 3164789327 | C4: 3007277888 | D4: 3077685183 | E4: 3886899018 | F4: 5175562196
A5: Projects under construction | B5: 73964179 | C5: 127380566 | D5: 299334840 | E5: 1511945561 | F5: 2722175926
A6: Plant wealth | B6: 49752884 | C6: 64319246 | D6: 0 | E6: 0 | F6: 0
A7: Biological assets | B7: 196194420 | C7: 197472085 | D7: 305114220 | E7: 445704631 | F7: 574493531
A8: Equity investments | B8: 15116843 | C8: 16926093 | D8: 15670070 | E8: 18025552 | F8: 0
A9: Investment at amortised cost (LT) | B9: 0 | C9: 0 | D9: 0 | E9: 0 | F9: 109946586
A10: Right-of-use assets | B10: 61583843 | C10: 47182377 | D10: 38966498 | E10: 93038704 | F10: 184421330
A11: Goodwill | B11: 97092890 | C11: 97092890 | D11: 97092890 | E11: 97092890 | F11: 97092890
A12: Other non-current assets | B12: 723872 | C12: 715600 | D12: 707329 | E12: 0 | F12: 690785
A13: Total non-current assets | B13: =SUM(B4:B12) -> 3659218258 | C13: =SUM(C4:C12) -> 3558366745 | D13: =SUM(D4:D12) -> 3834571030 | E13: =SUM(E4:E12) -> 6052706356 | F13: =SUM(F4:F12) -> 8864383244
A14: Current assets
A15: Inventory | B15: 879266088 | C15: 1725513368 | D15: 2783515178 | E15: 4177070922 | F15: 5815744221
A16: Trade & other receivables | B16: 456020949 | C16: 768124141 | D16: 834918362 | E16: 1501832833 | F16: 2033905286
A17: Current biological assets | B17: 10617902 | C17: 20276099 | D17: 29465780 | E17: 0 | F17: 66662132
A18: Assets held for sale | B18: 1607427 | C18: 1942496 | D18: 0 | E18: 0 | F18: 0
A19: Due from related parties | B19: 2966 | C19: 559970 | D19: 2760164 | E19: 3421436 | F19: 0
A20: Other current assets | B20: 0 | C20: 0 | D20: 0 | E20: 44186478 | F20: 0
A21: Investment at amortised cost (ST) | B21: 0 | C21: 0 | D21: 1610291 | E21: 0 | F21: 537771276
A22: Cash & cash equivalents | B22: 453015330 | C22: 294504052 | D22: 1093526328 | E22: 1811244599 | F22: 1091755742
A23: Total current assets | B23: =SUM(B15:B22) -> 1800530662 | C23: =SUM(C15:C22) -> 2810920126 | D23: =SUM(D15:D22) -> 4745796103 | E23: =SUM(E15:E22) -> 7537756268 | F23: =SUM(F15:F22) -> 9545838657
A24: TOTAL ASSETS | B24: =B13+B23 -> 5459748920 | C24: =C13+C23 -> 6369286871 | D24: =D13+D23 -> 8580367133 | E24: =E13+E23 -> 13590462624 | F24: =F13+F23 -> 18410221901

Sheet Cash Flow
A1: Statement of Cash Flows (EGP)
A2: Line item (EGP) | B2: 2021 | C2: 2022 | D2: 2023 | E2: 2024 | F2: 2025
A3: Net operating cash flow | B3: 768096649 | C3: 439908278 | D3: 1651546284 | E3: 2274844702 | F3: 777594355
A4: Net investing cash flow | B4: -200495770 | C4: -166813689 | D4: -738602093 | E4: -2901835696 | F4: -3708873743
A5: Net financing cash flow | B5: -298286463 | C5: -380096540 | D5: 49856453 | E5: 1529187259 | F5: 2289340385
A6: Net change in cash | B6: =B3+B4+B5 -> 269314416 | C6: =C3+C4+C5 -> -107001951 | D6: =D3+D4+D5 -> 962800644 | E6: =E3+E4+E5 -> 902196265 | F6: =F3+F4+F5 -> -641939003
A7: FX effect on cash | B7: 1158376 | C7: -51509327 | D7: -163778368 | E7: -184477994 | F7: -77548855
A8: Cash at beginning | B8: 182542538 | C8: 453015330 | D8: 294504052 | E8: 1093526328 | F8: 1811244599
A9: Cash at end (computed) | B9: =B8+B6+B7 -> 453015330 | C9: =C8+C6+C7 -> 294504052 | D9: =D8+D6+D7 -> 1093526328 | E9: =E8+E6+E7 -> 1811244599 | F9: =F8+F6+F7 -> 1091756741
A10: Cash per balance sheet (check) | B10: 453015330 | C10: 294504052 | D10: 1093526328 | E10: 1811244599 | F10: 1091755742
A11: ⚠ 2024 operating CF as in the 2024 statements (2,274.8mn); restated to 2,123.3mn in the 2025 comparatives after consolidation.

Sheet Working Capital
A1: Working Capital — Cash Conversion Cycle
A2: Item | B2: 2021 | C2: 2022 | D2: 2023 | E2: 2024 | F2: 2025
A3: Net revenue | B3: 8805974252 | C3: 11363960170 | D3: 15536190159 | E3: 24302616048 | F3: 29984446222
A4: Cost of sales (positive) | B4: 6278903539 | C4: 8458554544 | D4: 11926060448 | E4: 16912916624 | F4: 23103562055
A5: Inventory | B5: 879266088 | C5: 1725513368 | D5: 2783515178 | E5: 4177070922 | F5: 5815744221
A6: Receivables | B6: 456020949 | C6: 768124141 | D6: 834918362 | E6: 1501832833 | F6: 2033905286
A7: Payables (real 21-24, est 25) | B7: 928212428 | C7: 1340285565 | D7: 2261080629 | E7: 2006712301 | F7: 2800000000
A8: Days inventory (DIO) | B8: =B5/B4*365 -> 51.112765 | C8: =C5/C4*365 -> 74.45863 | D8: =D5/D4*365 -> 85.190164 | E8: =E5/E4*365 -> 90.145947 | F8: =F5/F4*365 -> 91.879626
A9: Days sales (DSO) | B9: =B6/B3*365 -> 18.901673 | C9: =C6/C3*365 -> 24.671444 | D9: =D6/D3*365 -> 19.615182 | E9: =E6/E3*365 -> 22.555966 | F9: =F6/F3*365 -> 24.758684
A10: Days payable (DPO) | B10: =B7/B4*365 -> 53.958073 | C10: =C7/C4*365 -> 57.835441 | D10: =D7/D4*365 -> 69.200926 | E10: =E7/E4*365 -> 43.307137 | F10: =F7/F4*365 -> 44.235603
A11: Cash conversion cycle (CCC) | B11: =B8+B9-B10 -> 16.056365 | C11: =C8+C9-C10 -> 41.294633 | D11: =D8+D9-D10 -> 35.60442 | E11: =E8+E9-E10 -> 69.394777 | F11: =F8+F9-F10 -> 72.402707
A12: ⚠ 2025 payables estimate (~2,800mn) pending the consolidated statement . DIO rose 51→92 days (defensive stockpiling).

Sheet Revenue Breakdown
A1: Revenue Breakdown 2023 — segments & exports
A2: Segment | B2: Revenue (EGP mn) | C2: Weight % | D2: Growth %
A3: Dairy | B3: 8528 | C3: 0.529 | D3: 0.4
A4: Chilled / yoghurt | B4: 3541 | C4: 0.22 | D4: 0.29
A5: Juice | B5: 2740 | C5: 0.17 | D5: 0.43
A6: Concentrates | B6: 1032 | C6: 0.064 | D6: 1.64
A7: Third-party distribution | B7: 287 | C7: 0.018 | D7: 0.24
A8: Total | B8: =SUM(B3:B7) -> 16128
A10: Domestic vs export (2023 → 2025)
A11: Item | B11: 2023 | C11: 2025
A12: Export revenue (EGP) | B12: ~1.2 bn | C12: 2.2 bn
A13: Export share | B13: ~7% | C13: ~7.3%
A14: In USD | B14: ~38 mn $ | C14: 46 mn $

Sheet Cost Breakdown
A1: Cost Breakdown — Note 4 & Note 17 (EGP)
A2: Cost component (Note 4) | B2: 2023 | C2: 2022 | D2: 2023 weight
A3: Raw materials, packaging & other | B3: 11379909322 | C3: 8090545850 | D3: 0.956
A4: Change in finished goods | B4: 313879771 | C4: 150718331 | D4: 0.026
A5: Depreciation | B5: 212622529 | C5: 217290363 | D5: 0.018
A6: Total cost of sales | B6: =SUM(B3:B5) -> 11906411622 | C6: =SUM(C3:C5) -> 8458554544
A8: Inventory composition (Note 17)
A9: Item | B9: 2023 | C9: 2022 | D9: Growth
A10: Raw materials | B10: 869035593 | C10: 514750127 | D10: 0.688
A11: Packaging | B11: 505755185 | C11: 486448453 | D11: 0.04
A12: Finished goods | B12: 875366224 | C12: 561486453 | D12: 0.559
A13: Supplies | B13: 150608669 | C13: 96617666 | D13: 0.559
A14: Goods in transit (L/C) | B14: 382749507 | C14: 66210669 | D14: 4.781
A15: ⚠ 95.6% of cost is materials & packaging (no cushion to absorb shocks). Goods in transit +478% = stockpiling of dollar imports in 2023.

Sheet FX Differences
A1: FX Differences — Reported vs Adjusted
A2: Item (EGP) | B2: 2022 | C2: 2023 | D2: 2024 | E2: 2025 | F2: Location
A3: FX loss in income statement | B3: -51509326 | C3: -163778368 | D3: -184477994 | E3: -77548855 | F3: Financing line — visible
A4: Loss shifted to OCI (EAS 13) | B4: 0 | C4: 0 | D4: -344814387 | E4: -348000000 | F4: OCI — outside the income statement
A5: Total real FX losses | B5: =B3+B4 -> -51509326 | C5: =C3+C4 -> -163778368 | D5: =D3+D4 -> -529292381 | E5: =E3+E4 -> -425548855
A7: Reported net profit | B7: 637999000 | C7: 1021460000 | D7: 2735395000 | E7: 1910095000
A8: EAS 13 adjustment | B8: 0 | C8: 0 | D8: -344814387 | E8: -348000000
A9: Adjusted (true) net profit | B9: =B7+B8 -> 637999000 | C9: =C7+C8 -> 1021460000 | D9: =D7+D8 -> 2390580613 | E9: =E7+E8 -> 1562095000
A10: Adjustment impact % | B10: =B9/B7-1 -> 0 | C10: =C9/C7-1 -> 0 | D10: =D9/D7-1 -> -0.12605652 | E10: =E9/E7-1 -> -0.18218989
A12: ⚠ 2024 EPS: reported 2.91 → adjusted 2.54. Management confirmed H1 2025 included 522mn of FX (adjusted gross margin 28.7%).

Sheet Leverage & Returns
A1: Financial Leverage & Returns — DuPont & ROIC
A2: Item | B2: 2021 | C2: 2022 | D2: 2023 | E2: 2024 | F2: 2025
A3: Total liabilities | B3: 2291432636 | C3: 2958554699 | D3: 4330598548 | E3: 7251138154 | F3: 10377677682
A4: Cash | B4: 453015330 | C4: 294504052 | D4: 1093526328 | E4: 1811244599 | F4: 1091755742
A5: Total equity | B5: 3168316284 | C5: 3410732172 | D5: 4249768585 | E5: 6339324470 | F5: 8032544219
A6: Total assets | B6: 5459748920 | C6: 6369286871 | D6: 8580367133 | E6: 13590462624 | F6: 18410221901
A7: Net debt | B7: =B3-B4 -> 1838417306 | C7: =C3-C4 -> 2664050647 | D7: =D3-D4 -> 3237072220 | E7: =E3-E4 -> 5439893555 | F7: =F3-F4 -> 9285921940
A8: Net debt / equity | B8: =B7/B5 -> 0.58025056 | C8: =C7/C5 -> 0.78107882 | D8: =D7/D5 -> 0.76170553 | E8: =E7/E5 -> 0.85811881 | F8: =F7/F5 -> 1.1560375
A9: Reported net profit | B9: 526389118 | C9: 637999000 | D9: 1021460218 | E9: 2735394516 | F9: 1910094835
A10: EAS 13 adjustment | B10: 0 | C10: 0 | D10: 0 | E10: -344814387 | F10: -348000000
A11: Adjusted net profit | B11: =B9+B10 -> 526389118 | C11: =C9+C10 -> 637999000 | D11: =D9+D10 -> 1021460218 | E11: =E9+E10 -> 2390580129 | F11: =F9+F10 -> 1562094835
A12: Avg equity | B12: 3168316284 | C12: 3289524228 | D12: 3.8302504e+09 | E12: 5.2945465e+09 | F12: 7.1859343e+09
A13: Avg assets | B13: 5459748920 | C13: 5.9145179e+09 | D13: 7474827002 | E13: 1.1085415e+10 | F13: 1.6000342e+10
A14: Adjusted ROE | B14: =B11/B12 -> 0.16614159 | C14: =C11/C12 -> 0.19394872 | D14: =D11/D12 -> 0.26668236 | E14: =E11/E12 -> 0.45151745 | F14: =F11/F12 -> 0.21738229
A15: Reported net margin | B15: =B9/'Income Statement'!B3 -> 0.059776364 | C15: =C9/'Income Statement'!C3 -> 0.056142312 | D15: =D9/'Income Statement'!D3 -> 0.063334187 | E15: =E9/'Income Statement'!E3 -> 0.11255556 | F15: =F9/'Income Statement'!F3 -> 0.063702855
A16: Asset turnover | B16: ='Income Statement'!B3/B13 -> 1.61289 | C16: ='Income Statement'!C3/C13 -> 1.9213671 | D16: ='Income Statement'!D3/D13 -> 2.1576555 | E16: ='Income Statement'!E3/E13 -> 2.1923055 | F16: ='Income Statement'!F3/F13 -> 1.8739878
A17: Leverage (assets/equity) | B17: =B13/B12 -> 1.7232336 | C17: =C13/C12 -> 1.7979858 | D17: =D13/D12 -> 1.9515244 | E17: =E13/E12 -> 2.0937421 | F17: =F13/F12 -> 2.2266196
A18: DuPont check (=ROE) | B18: =B15*B16*B17 -> 0.16614159 | C18: =C15*C16*C17 -> 0.19394872 | D18: =D15*D16*D17 -> 0.26668236 | E18: =E15*E16*E17 -> 0.51664378 | F18: =F15*F16*F17 -> 0.26581023
A19: Interest coverage | B19: 12.23 | C19: 8.312 | D19: 5.615 | E19: 7.868 | F19: 3.057
A20: Gross→operating conversion | B20: 0.33 | C20: 0.353 | D20: 0.427 | E20: 0.635 | F20: 0.519
A21: NOPAT (operating×0.75) | B21: 6.2544043e+08 | C21: 768709476 | D21: 1.3514472e+09 | E21: 3.5197331e+09 | F21: 2.6799691e+09
A22: Invested capital (eq+net debt) | B22: =B5+B7 -> 5006733590 | C22: =C5+C7 -> 6074782819 | D22: =D5+D7 -> 7486840805 | E22: =E5+E7 -> 11779218025 | F22: =F5+F7 -> 17318466159
A23: ROIC | B23: =B21/B22 -> 0.12491985 | C23: =C21/AVERAGE(B22:C22) -> 0.13873724 | D23: =D21/AVERAGE(C22:D22) -> 0.19930463 | E23: =E21/AVERAGE(D22:E22) -> 0.36538175 | F23: =F21/AVERAGE(E22:F22) -> 0.18420497
A24: ⚠ Returns look strong, but in 2025 margin and turnover fell while leverage alone rose — return increasingly comes from borrowing, not operations. Interest coverage collapsed 12.2x → 3.1x.

Sheet Valuation
A1: Valuation
A2: Item | B2: Value
A3: Share price (EGP) — edit here | B3: 29.3
A4: Shares outstanding | B4: 1176756353
A5: Market capitalisation | B5: =B3*B4 -> 3.4478961e+10
A6: Net debt 2025 | B6: 9285921940
A7: Enterprise value (EV) | B7: =B5+B6 -> 4.3764883e+10
A8: Reported net profit 2025 | B8: 1910095000
A9: Adjusted net profit 2025 | B9: 1562095000
A10: Business-results profit 2025 | B10: 2253000000
A11: EBITDA 2025 | B11: 4634000000
A12: EPS reported | B12: =B8/B4 -> 1.6231865
A13: EPS adjusted | B13: =B9/B4 -> 1.3274583
A14: P/E reported | B14: =B3/B12 -> 18.050914
A15: P/E adjusted (the key one) | B15: =B3/B13 -> 22.072256
A16: EV/EBITDA | B16: =B7/B11 -> 9.4442993
A17: P/S (Price/Sales) | B17: =B5/'Income Statement'!F3 -> 1.1498949
A18: Earnings yield (adjusted) | B18: =1/B15 -> 0.045305744
A19: ⚠ Adjustment changes the decision: 13.3x on business-results profit, 18.1x on reported, but 22.1x on adjusted — dearer than it first appears.

Sheet 2026 Forecast
A1: 2026 Forecast — full year
A2: Scenario | B2: Growth | C2: 2026 revenue (mn)
A3: Conservative | B3: 0.2 | C3: =29984.446*(1+B3) -> 35981.335
A4: Base | B4: 0.24 | C4: =29984.446*(1+B4) -> 37180.713
A5: Optimistic | B5: 0.28 | C5: =29984.446*(1+B5) -> 38380.091
A7: Quarterly split (base scenario)
A8: Quarter | B8: Share | C8: Revenue (mn) | D8: Expected margin | E8: Gross profit
A9: Q1 2026 (actual) | B9: 0.23 | C9: 8600 | D9: 0.252 | E9: =C9*D9 -> 2167.2
A10: Q2 2026 | B10: 0.27 | C10: =$C$4*B10 -> 10038.793 | D10: 0.245 | E10: =C10*D10 -> 2459.5042
A11: Q3 2026 | B11: 0.26 | C11: =$C$4*B11 -> 9666.9854 | D11: 0.235 | E11: =C11*D11 -> 2271.7416
A12: Q4 2026 | B12: 0.24 | C12: =$C$4*B12 -> 8923.3711 | D12: 0.23 | E12: =C12*D12 -> 2052.3754
A13: Total 2026 | C13: =SUM(C9:C12) -> 37229.149 | E13: =SUM(E9:E12) -> 8950.8211
A15: ⚠ Ramadan 2026 fell entirely in Q1, so Q1 carries the highest margin and later quarters are weaker — a forecast built on the confirmed pattern.

Sheet Management Commentary
A1: Management Commentary — documented findings
A2: Topic | B2: What was said | C2: Implication
A3: The 2024 jump | B3: Global orange-concentrate prices hit records in 2024 and fell in 2025 | C3: Temporary, unsustainable — explains +200% then −56% in concentrates
A4: Turning point Q4-25 | B4: Profit +115% and EBITDA +87% after the concentrate base faded | C4: Final confirmation that 2024 was exceptional
A5: Formal normalisation | B5: Adjusted FY24: 28.3% margin vs 30.4% and ~2,386mn profit | C5: Management itself confirms the EAS 13 adjustment
A6: Geographic expansion | B6: 48 countries + Al-Rashed partnership in Saudi Arabia | C6: Start of a natural hedge
A7: New products | B7: Pudding (late 2024) in three flavours | C7: Innovation drives volumes
A8: Ramadan | B8: Demand surge on products during Ramadan | C8: Supports the discovered seasonality pattern
A9: Merger Feb 2025 | B9: March alone added 1.2bn gross profit to retained earnings | C9: Explains the gap between business results and statements
A10: Bekhero | B10: Value brand 37% of dairy | C10: Evidence of consumers trading down
